guided_tamp_benchmark/benchmark/__init__.py
guided_tamp_benchmark/benchmark/benchmark.py
guided_tamp_benchmark/benchmark/benchmark_result.py
guided_tamp_benchmark/core/__init__.py
guided_tamp_benchmark/core/configuration.py
guided_tamp_benchmark/core/path.py
guided_tamp_benchmark/core/planner.py
guided_tamp_benchmark/models/__init__.py
guided_tamp_benchmark/models/data/robots/franka_panda/meshes/collision/finger.obj
guided_tamp_benchmark/models/data/robots/franka_panda/meshes/collision/finger.stl
guided_tamp_benchmark/models/data/robots/franka_panda/meshes/collision/hand.obj
guided_tamp_benchmark/models/data/robots/franka_panda/meshes/collision/hand.stl
guided_tamp_benchmark/models/data/robots/franka_panda/meshes/collision/link0.obj
guided_tamp_benchmark/models/data/robots/franka_panda/meshes/collision/link0.stl
guided_tamp_benchmark/models/data/robots/franka_panda/meshes/collision/link1.obj
guided_tamp_benchmark/models/data/robots/franka_panda/meshes/collision/link1.stl
guided_tamp_benchmark/models/data/robots/franka_panda/meshes/collision/link2.obj
guided_tamp_benchmark/models/data/robots/franka_panda/meshes/collision/link2.stl
guided_tamp_benchmark/models/data/robots/franka_panda/meshes/collision/link3.obj
guided_tamp_benchmark/models/data/robots/franka_panda/meshes/collision/link3.stl
guided_tamp_benchmark/models/data/robots/franka_panda/meshes/collision/link4.obj
guided_tamp_benchmark/models/data/robots/franka_panda/meshes/collision/link4.stl
guided_tamp_benchmark/models/data/robots/franka_panda/meshes/collision/link5.obj
guided_tamp_benchmark/models/data/robots/franka_panda/meshes/collision/link5.stl
guided_tamp_benchmark/models/data/robots/franka_panda/meshes/collision/link6.mtl
guided_tamp_benchmark/models/data/robots/franka_panda/meshes/collision/link6.obj
guided_tamp_benchmark/models/data/robots/franka_panda/meshes/collision/link6.stl
guided_tamp_benchmark/models/data/robots/franka_panda/meshes/collision/link7.obj
guided_tamp_benchmark-0.1.0.dist-info/LICENSE
guided_tamp_benchmark-0.1.0.dist-info/METADATA
guided_tamp_benchmark-0.1.0.dist-info/WHEEL
guided_tamp_benchmark-0.1.0.dist-info/RECORD
