Metadata-Version: 2.1
Name: guided-tamp-benchmark
Version: 0.1.0
Summary: Benchmark for guided task and motion planning for manipulation tasks.
License: BSD-2-Clause license
Author: Kateryna Zorina
Author-email: zorinkat@fbmi.cvut.cz
Requires-Python: >=3.8,<4.0
Classifier: License :: Other/Proprietary License
Classifier: Programming Language :: Python :: 3
Classifier: Programming Language :: Python :: 3.8
Classifier: Programming Language :: Python :: 3.9
Classifier: Programming Language :: Python :: 3.10
Classifier: Programming Language :: Python :: 3.11
Requires-Dist: dill (>=0.3.6,<0.4.0)
Requires-Dist: numpy (>=1.24.2,<2.0.0)
Requires-Dist: pin (>=2.6.17,<3.0.0)
Requires-Dist: robomeshcat (>=1.1.1,<2.0.0)
